speedrunapi/__init__.py
speedrunapi/categories.py
speedrunapi/errors.py
speedrunapi/game_data.py
speedrunapi/leaderboard.py
speedrunapi/levels.py
speedrunapi/regions.py
speedrunapi/runs.py
speedrunapi/speedrunapi.py
speedrunapi/translation.py
speedrunapi/user_data.py
speedrunapi-0.6.0.dist-info/LICENSE
speedrunapi-0.6.0.dist-info/METADATA
speedrunapi-0.6.0.dist-info/WHEEL
speedrunapi-0.6.0.dist-info/top_level.txt
speedrunapi-0.6.0.dist-info/RECORD
