Metadata-Version: 2.1
Name: speedrunapi
Version: 0.6.0
Summary: A library for working with speerun.coms API
Author: Connor (fishin_rod)
Project-URL: Homepage, https://github.com/fishin-rod/speedrunapi
Project-URL: Bug Tracker, https://github.com/fishin-rod/speedrunapi/issues
Project-URL: Documentation, https://speedrunapi.readthedocs.io
Classifier: Programming Language :: Python :: 3
Classifier: License :: OSI Approved :: MIT License
Classifier: Operating System :: OS Independent
Requires-Python: >=3.7
License-File: LICENSE
